Metadata-Version: 2.1
Name: gruut-lang-cs
Version: 1.3.1
Summary: Czech language files for gruut tokenizer/phonemizer
Home-page: https://github.com/rhasspy/gruut
Author: Michael Hansen
Author-email: mike@rhasspy.org
License: UNKNOWN
Platform: UNKNOWN
Classifier: Programming Language :: Python :: 3
Classifier: License :: OSI Approved :: MIT License
